tinyprofiler/__init__.py
tinyprofiler/main.py
tinyprofiler-0.1.8.dist-info/METADATA
tinyprofiler-0.1.8.dist-info/WHEEL
tinyprofiler-0.1.8.dist-info/top_level.txt
tinyprofiler-0.1.8.dist-info/RECORD
