Metadata-Version: 2.1
Name: tinyprofiler
Version: 0.1.8
Summary: A Profiling Library for Python
Home-page: UNKNOWN
Author: Carter Fulcher
Author-email: fulcher.carter@gmail.com
License: UNKNOWN
Platform: UNKNOWN
